elapsed_time/__init__.py
elapsed_time/elapsed_time.py
elapsed_time-1.1.dist-info/LICENSE
elapsed_time-1.1.dist-info/METADATA
elapsed_time-1.1.dist-info/WHEEL
elapsed_time-1.1.dist-info/top_level.txt
elapsed_time-1.1.dist-info/RECORD
