Metadata-Version: 2.1
Name: elapsed-time
Version: 1.1
Summary: Measure exec time of a Python function
Home-page: https://github.com/Estebandotpy/elapsed_time
Author: Esteban Osorio
Author-email: estebandmp17@gmail.com
License: MIT
Keywords: testing,example
License-File: LICENSE
